{
   "login":{
    "key": "06b72d1875c4c2a4636e8e6f2bc7834806547c8e"
},
   "posts":[
      {
         "id":1,
         "title":"hello"
      }
   ],
   "cliente":{
      "id":1,
      "nombre":"Ines Tornudo",
      "cedula":13336668,
      "direccion":"Cerro Bajo 2032"
   },
   "servicios":[
      {
         "id":1,
         "cliente_id":1,
         "odometro":1000
      },
      {
         "id":2,
         "cliente_id":1,
         "odometro":5000
      },
      {
         "id":3,
         "cliente_id":2,
         "odometro":1000
      },
      {
         "id":4,
         "cliente_id":2,
         "odometro":5000
      },
      {
         "id":5,
         "cliente_id":2,
         "odometro":15000
      }
   ]
}
